pycram/__init__.py
pycram/cache_manager.py
pycram/costmaps.py
pycram/description.py
pycram/designator.py
pycram/failure_handling.py
pycram/failures.py
pycram/filter.py
pycram/fluent.py
pycram/graph_of_convex_sets.py
pycram/has_parameters.py
pycram/helper.py
pycram/language.py
pycram/local_transformer.py
pycram/parameterizer.py
pycram/plan.py
pycram/pose_generator_and_validator.py
pycram/probabilistic_costmap.py
pycram/process_module.py
pycram/robot_description.py
pycram/testing.py
pycram/tf_transformations.py
pycram/units.py
pycram/utils.py
pycram/world_reasoning.py
pycram/config/__init__.py
pycram/config/action_conf.py
pycram/config/ik_conf.py
pycram/config/multiverse_conf.py
pycram/config/world_conf.py
pycram/datastructures/__init__.py
pycram/datastructures/dataclasses.py
pycram/datastructures/enums.py
pycram/datastructures/grasp.py
pycram/datastructures/mixins.py
pycram/datastructures/partial_designator.py
pycram/datastructures/pose.py
pycram/datastructures/world.py
pycram/datastructures/world_entity.py
pycram/designators/GAP.py
pycram/designators/__init__.py
pycram/designators/action_designator.py
pycram/designators/location_designator.py
pycram/designators/motion_designator.py
pycram/designators/object_designator.py
pycram/designators/specialized_designators/__init__.py
pycram/designators/specialized_designators/action/__init__.py
pycram/designators/specialized_designators/action/dual_arm_pickup_action.py
pycram/designators/specialized_designators/location/__init__.py
pycram/designators/specialized_designators/location/database_location.py
pycram/designators/specialized_designators/location/giskard_location.py
pycram/designators/specialized_designators/probabilistic/__init__.py
pycram/designators/specialized_designators/probabilistic/probabilistic_action.py
pycram/external_interfaces/__init__.py
pycram/external_interfaces/blum_api.py
pycram/external_interfaces/giskard.py
pycram/external_interfaces/ik.py
pycram/external_interfaces/knowrob.py
pycram_robotics-1.0.4.dist-info/licenses/LICENSE
pycram_robotics-1.0.4.dist-info/METADATA
pycram_robotics-1.0.4.dist-info/WHEEL
pycram_robotics-1.0.4.dist-info/top_level.txt
pycram_robotics-1.0.4.dist-info/zip-safe
pycram_robotics-1.0.4.dist-info/RECORD
