Metadata-Version: 2.4
Name: pycram-robotics
Version: 1.0.4
Summary: A Python library for cognitive robot control
Maintainer: Jonas Dech
Maintainer-email: jdech@uni-bremen.de
License: Gplv3
License-File: LICENSE
Requires-Dist: setuptools
Requires-Dist: pycram_bullet
Requires-Dist: numpy
Requires-Dist: pytransform3d
Requires-Dist: typing_extensions>=4.10.0
Requires-Dist: trimesh==4.6.0
Requires-Dist: random_events>=4.1.0
Requires-Dist: pin==2.7.0
Requires-Dist: transforms3d
Requires-Dist: python-box
Requires-Dist: urdf_parser_py
Requires-Dist: networkx
Requires-Dist: pint
Requires-Dist: owlready2>=0.45
Requires-Dist: psutil
Requires-Dist: deprecated
Requires-Dist: plotly
Requires-Dist: sortedcontainers
Requires-Dist: probabilistic_model
Requires-Dist: manifold3d
Dynamic: description
Dynamic: description-content-type
Dynamic: license
Dynamic: license-file
Dynamic: maintainer
Dynamic: maintainer-email
Dynamic: requires-dist
Dynamic: summary
